{
    "version": "https://jsonfeed.org/version/1",
    "title": "Vrancich.com",
    "description": "",
    "home_page_url": "https://vrancich.com",
    "feed_url": "https://vrancich.com/feed.json",
    "user_comment": "",
    "author": {
        "name": "Maja Vrancich"
    },
    "items": [
        {
            "id": "https://vrancich.com/did-you-find-the-one-you-wanted.html",
            "url": "https://vrancich.com/did-you-find-the-one-you-wanted.html",
            "title": "Did you find the one you wanted?",
            "summary": "[{\"id\":1555941466744,\"type\":\"publii-paragraph\",\"content\":\":)\",\"config\":{\"textAlign\":\"left\",\"advanced\":{\"style\":\"\",\"cssClasses\":\"\",\"id\":\"\"}}}]",
            "content_html": "[{\"id\":1555941466744,\"type\":\"publii-paragraph\",\"content\":\":)\",\"config\":{\"textAlign\":\"left\",\"advanced\":{\"style\":\"\",\"cssClasses\":\"\",\"id\":\"\"}}}]",
            "author": {
                "name": "Maja Vrancich"
            },
            "tags": [
            ],
            "date_published": "2020-11-28T22:02:51+01:00",
            "date_modified": "2020-11-28T22:02:51+01:00"
        },
        {
            "id": "https://vrancich.com/welcome.html",
            "url": "https://vrancich.com/welcome.html",
            "title": "Who are you looking for?",
            "summary": "This is homepage of our familly. You could be intrested to learn about Maja or Moreno.for Maja's site ::click here::and for Moreno's ::click here::",
            "content_html": "<p>This is homepage of our familly.<br><br>You could be intrested to learn about Maja or Moreno.</p>\n<ul>\n<li>for Maja's site <a href=\"https://maja.vrancich.com\" title=\"maja.vrancich.com\">::click here::</a></li>\n<li>and for Moreno's <a href=\"https://moreno.vrancich.com\" title=\"moreno.vrancich.com\">::click here::</a></li>\n</ul>",
            "author": {
                "name": "Maja Vrancich"
            },
            "tags": [
            ],
            "date_published": "2020-06-15T15:10:28+02:00",
            "date_modified": "2020-06-16T15:38:12+02:00"
        }
    ]
}
